[
    {
        "__typename": "GraphImage",
        "comments_disabled": false,
        "dimensions": {
            "height": 1350,
            "width": 1080
        },
        "display_url": "https://instagram.fsaw1-6.fna.fbcdn.net/t51.2885-15/e35/23594923_349861228812417_4024207141706399744_n.jpg",
        "edge_media_preview_like": {
            "count": 124
        },
        "edge_media_to_caption": {
            "edges": [
                {
                    "node": {
                        "text": "Sensin tosbağa\n\n#vintage #old #classic #vosvos #wolksvagen #beetle"
                    }
                }
            ]
        },
        "edge_media_to_comment": {
            "count": 0
        },
        "id": "1650868692361573634",
        "is_video": false,
        "owner": {
            "id": "1942768511"
        },
        "shortcode": "BbpEFQ7BnUC",
        "tags": [
            "vintage",
            "old",
            "classic",
            "beetle",
            "vosvos",
            "wolksvagen"
        ],
        "taken_at_timestamp": 1511018905,
        "thumbnail_resources": [
            {
                "config_height": 150,
                "config_width": 150,
                "src": "https://instagram.fsaw1-6.fna.fbcdn.net/t51.2885-15/s150x150/e35/c0.135.1080.1080/23594923_349861228812417_4024207141706399744_n.jpg"
            },
            {
                "config_height": 240,
                "config_width": 240,
                "src": "https://instagram.fsaw1-6.fna.fbcdn.net/t51.2885-15/s240x240/e35/c0.135.1080.1080/23594923_349861228812417_4024207141706399744_n.jpg"
            },
            {
                "config_height": 320,
                "config_width": 320,
                "src": "https://instagram.fsaw1-6.fna.fbcdn.net/t51.2885-15/s320x320/e35/c0.135.1080.1080/23594923_349861228812417_4024207141706399744_n.jpg"
            },
            {
                "config_height": 480,
                "config_width": 480,
                "src": "https://instagram.fsaw1-6.fna.fbcdn.net/t51.2885-15/s480x480/e35/c0.135.1080.1080/23594923_349861228812417_4024207141706399744_n.jpg"
            },
            {
                "config_height": 640,
                "config_width": 640,
                "src": "https://instagram.fsaw1-6.fna.fbcdn.net/t51.2885-15/s640x640/sh0.08/e35/c0.135.1080.1080/23594923_349861228812417_4024207141706399744_n.jpg"
            }
        ],
        "thumbnail_src": "https://instagram.fsaw1-6.fna.fbcdn.net/t51.2885-15/s640x640/sh0.08/e35/c0.135.1080.1080/23594923_349861228812417_4024207141706399744_n.jpg",
        "urls": [
            "https://instagram.fsaw1-6.fna.fbcdn.net/t51.2885-15/e35/23594923_349861228812417_4024207141706399744_n.jpg"
        ]
    },
    {
        "__typename": "GraphImage",
        "comments_disabled": false,
        "dimensions": {
            "height": 414,
            "width": 750
        },
        "display_url": "https://instagram.fsaw1-6.fna.fbcdn.net/t51.2885-15/e35/22710703_123778658288811_7800801593367986176_n.jpg",
        "edge_media_preview_like": {
            "count": 162
        },
        "edge_media_to_caption": {
            "edges": [
                {
                    "node": {
                        "text": "This is what autumn does to me 🍂🍁 #thegreatoutdoors"
                    }
                }
            ]
        },
        "edge_media_to_comment": {
            "count": 1
        },
        "id": "1634201749445435194",
        "is_video": false,
        "owner": {
            "id": "1942768511"
        },
        "shortcode": "Bat2dUvBF86",
        "tags": [
            "thegreatoutdoors"
        ],
        "taken_at_timestamp": 1509032051,
        "thumbnail_resources": [
            {
                "config_height": 150,
                "config_width": 150,
                "src": "https://instagram.fsaw1-6.fna.fbcdn.net/t51.2885-15/s150x150/e35/c168.0.414.414/22710703_123778658288811_7800801593367986176_n.jpg"
            },
            {
                "config_height": 240,
                "config_width": 240,
                "src": "https://instagram.fsaw1-6.fna.fbcdn.net/t51.2885-15/s240x240/e35/c168.0.414.414/22710703_123778658288811_7800801593367986176_n.jpg"
            },
            {
                "config_height": 320,
                "config_width": 320,
                "src": "https://instagram.fsaw1-6.fna.fbcdn.net/t51.2885-15/s320x320/e35/c168.0.414.414/22710703_123778658288811_7800801593367986176_n.jpg"
            },
            {
                "config_height": 480,
                "config_width": 480,
                "src": "https://instagram.fsaw1-6.fna.fbcdn.net/t51.2885-15/e35/c168.0.414.414/22710703_123778658288811_7800801593367986176_n.jpg"
            },
            {
                "config_height": 640,
                "config_width": 640,
                "src": "https://instagram.fsaw1-6.fna.fbcdn.net/t51.2885-15/e35/c168.0.414.414/22710703_123778658288811_7800801593367986176_n.jpg"
            }
        ],
        "thumbnail_src": "https://instagram.fsaw1-6.fna.fbcdn.net/t51.2885-15/e35/c168.0.414.414/22710703_123778658288811_7800801593367986176_n.jpg",
        "urls": [
            "https://instagram.fsaw1-6.fna.fbcdn.net/t51.2885-15/e35/22710703_123778658288811_7800801593367986176_n.jpg"
        ]
    },
    {
        "__typename": "GraphImage",
        "comments_disabled": false,
        "dimensions": {
            "height": 607,
            "width": 1080
        },
        "display_url": "https://instagram.fsaw1-6.fna.fbcdn.net/t51.2885-15/e35/21909315_824831341013056_8654929288413315072_n.jpg",
        "edge_media_preview_like": {
            "count": 164
        },
        "edge_media_to_caption": {
            "edges": [
                {
                    "node": {
                        "text": "I was the black sheep of the family 🐾 #tb #aroundtheworld"
                    }
                }
            ]
        },
        "edge_media_to_comment": {
            "count": 4
        },
        "id": "1608893074565935109",
        "is_video": false,
        "owner": {
            "id": "1942768511"
        },
        "shortcode": "BZT77ofFrAF",
        "tags": [
            "tb",
            "aroundtheworld"
        ],
        "taken_at_timestamp": 1506015022,
        "thumbnail_resources": [
            {
                "config_height": 150,
                "config_width": 150,
                "src": "https://instagram.fsaw1-6.fna.fbcdn.net/t51.2885-15/s150x150/e35/c236.0.607.607/21909315_824831341013056_8654929288413315072_n.jpg"
            },
            {
                "config_height": 240,
                "config_width": 240,
                "src": "https://instagram.fsaw1-6.fna.fbcdn.net/t51.2885-15/s240x240/e35/c236.0.607.607/21909315_824831341013056_8654929288413315072_n.jpg"
            },
            {
                "config_height": 320,
                "config_width": 320,
                "src": "https://instagram.fsaw1-6.fna.fbcdn.net/t51.2885-15/s320x320/e35/c236.0.607.607/21909315_824831341013056_8654929288413315072_n.jpg"
            },
            {
                "config_height": 480,
                "config_width": 480,
                "src": "https://instagram.fsaw1-6.fna.fbcdn.net/t51.2885-15/s480x480/e35/c236.0.607.607/21909315_824831341013056_8654929288413315072_n.jpg"
            },
            {
                "config_height": 640,
                "config_width": 640,
                "src": "https://instagram.fsaw1-6.fna.fbcdn.net/t51.2885-15/e35/c236.0.607.607/21909315_824831341013056_8654929288413315072_n.jpg"
            }
        ],
        "thumbnail_src": "https://instagram.fsaw1-6.fna.fbcdn.net/t51.2885-15/e35/c236.0.607.607/21909315_824831341013056_8654929288413315072_n.jpg",
        "urls": [
            "https://instagram.fsaw1-6.fna.fbcdn.net/t51.2885-15/e35/21909315_824831341013056_8654929288413315072_n.jpg"
        ]
    },
    {
        "__typename": "GraphImage",
        "comments_disabled": false,
        "dimensions": {
            "height": 700,
            "width": 1080
        },
        "display_url": "https://instagram.fsaw1-6.fna.fbcdn.net/t51.2885-15/e35/21568966_1970258579910347_910537159855833088_n.jpg",
        "edge_media_preview_like": {
            "count": 149
        },
        "edge_media_to_caption": {
            "edges": [
                {
                    "node": {
                        "text": "Beklenen maximum reklamı #aroundtheworld"
                    }
                }
            ]
        },
        "edge_media_to_comment": {
            "count": 0
        },
        "id": "1600164950314255258",
        "is_video": false,
        "owner": {
            "id": "1942768511"
        },
        "shortcode": "BY07YtVgwOa",
        "tags": [
            "aroundtheworld"
        ],
        "taken_at_timestamp": 1504974548,
        "thumbnail_resources": [
            {
                "config_height": 150,
                "config_width": 150,
                "src": "https://instagram.fsaw1-6.fna.fbcdn.net/t51.2885-15/s150x150/e35/c190.0.700.700/21568966_1970258579910347_910537159855833088_n.jpg"
            },
            {
                "config_height": 240,
                "config_width": 240,
                "src": "https://instagram.fsaw1-6.fna.fbcdn.net/t51.2885-15/s240x240/e35/c190.0.700.700/21568966_1970258579910347_910537159855833088_n.jpg"
            },
            {
                "config_height": 320,
                "config_width": 320,
                "src": "https://instagram.fsaw1-6.fna.fbcdn.net/t51.2885-15/s320x320/e35/c190.0.700.700/21568966_1970258579910347_910537159855833088_n.jpg"
            },
            {
                "config_height": 480,
                "config_width": 480,
                "src": "https://instagram.fsaw1-6.fna.fbcdn.net/t51.2885-15/s480x480/e35/c190.0.700.700/21568966_1970258579910347_910537159855833088_n.jpg"
            },
            {
                "config_height": 640,
                "config_width": 640,
                "src": "https://instagram.fsaw1-6.fna.fbcdn.net/t51.2885-15/s640x640/sh0.08/e35/c190.0.700.700/21568966_1970258579910347_910537159855833088_n.jpg"
            }
        ],
        "thumbnail_src": "https://instagram.fsaw1-6.fna.fbcdn.net/t51.2885-15/s640x640/sh0.08/e35/c190.0.700.700/21568966_1970258579910347_910537159855833088_n.jpg",
        "urls": [
            "https://instagram.fsaw1-6.fna.fbcdn.net/t51.2885-15/e35/21568966_1970258579910347_910537159855833088_n.jpg"
        ]
    },
    {
        "__typename": "GraphImage",
        "comments_disabled": false,
        "dimensions": {
            "height": 1349,
            "width": 1080
        },
        "display_url": "https://instagram.fsaw1-6.fna.fbcdn.net/t51.2885-15/e35/21373696_1881217898808984_95700955210711040_n.jpg",
        "edge_media_preview_like": {
            "count": 200
        },
        "edge_media_to_caption": {
            "edges": [
                {
                    "node": {
                        "text": "Time for training probably 👊🏻 #aroundtheworld #dancinghouse #prague #ITUluyurtdisinda"
                    }
                }
            ]
        },
        "edge_media_to_comment": {
            "count": 1
        },
        "id": "1598741902499489961",
        "is_video": false,
        "owner": {
            "id": "1942768511"
        },
        "shortcode": "BYv30oyA6ip",
        "tags": [
            "prague",
            "ITUluyurtdisinda",
            "aroundtheworld",
            "dancinghouse"
        ],
        "taken_at_timestamp": 1504804908,
        "thumbnail_resources": [
            {
                "config_height": 150,
                "config_width": 150,
                "src": "https://instagram.fsaw1-6.fna.fbcdn.net/t51.2885-15/s150x150/e35/c0.110.881.881/21373696_1881217898808984_95700955210711040_n.jpg"
            },
            {
                "config_height": 240,
                "config_width": 240,
                "src": "https://instagram.fsaw1-6.fna.fbcdn.net/t51.2885-15/s240x240/e35/c0.110.881.881/21373696_1881217898808984_95700955210711040_n.jpg"
            },
            {
                "config_height": 320,
                "config_width": 320,
                "src": "https://instagram.fsaw1-6.fna.fbcdn.net/t51.2885-15/s320x320/e35/c0.110.881.881/21373696_1881217898808984_95700955210711040_n.jpg"
            },
            {
                "config_height": 480,
                "config_width": 480,
                "src": "https://instagram.fsaw1-6.fna.fbcdn.net/t51.2885-15/s480x480/e35/c0.110.881.881/21373696_1881217898808984_95700955210711040_n.jpg"
            },
            {
                "config_height": 640,
                "config_width": 640,
                "src": "https://instagram.fsaw1-6.fna.fbcdn.net/t51.2885-15/s640x640/sh0.08/e35/c0.110.881.881/21373696_1881217898808984_95700955210711040_n.jpg"
            }
        ],
        "thumbnail_src": "https://instagram.fsaw1-6.fna.fbcdn.net/t51.2885-15/s640x640/sh0.08/e35/c0.110.881.881/21373696_1881217898808984_95700955210711040_n.jpg",
        "urls": [
            "https://instagram.fsaw1-6.fna.fbcdn.net/t51.2885-15/e35/21373696_1881217898808984_95700955210711040_n.jpg"
        ]
    },
    {
        "__typename": "GraphImage",
        "comments_disabled": false,
        "dimensions": {
            "height": 1223,
            "width": 1080
        },
        "display_url": "https://instagram.fsaw1-6.fna.fbcdn.net/t51.2885-15/e35/19534841_120481221902052_5708394887984971776_n.jpg",
        "edge_media_preview_like": {
            "count": 133
        },
        "edge_media_to_caption": {
            "edges": [
                {
                    "node": {
                        "text": "Roam if you want to without wings, without wheels ☀️🇬🇷#aroundtheworld"
                    }
                }
            ]
        },
        "edge_media_to_comment": {
            "count": 0
        },
        "id": "1550844181362465492",
        "is_video": false,
        "owner": {
            "id": "1942768511"
        },
        "shortcode": "BWFtJD0F1rU",
        "tags": [
            "aroundtheworld"
        ],
        "taken_at_timestamp": 1499095054,
        "thumbnail_resources": [
            {
                "config_height": 150,
                "config_width": 150,
                "src": "https://instagram.fsaw1-6.fna.fbcdn.net/t51.2885-15/s150x150/e35/c0.56.850.850/19534841_120481221902052_5708394887984971776_n.jpg"
            },
            {
                "config_height": 240,
                "config_width": 240,
                "src": "https://instagram.fsaw1-6.fna.fbcdn.net/t51.2885-15/s240x240/e35/c0.56.850.850/19534841_120481221902052_5708394887984971776_n.jpg"
            },
            {
                "config_height": 320,
                "config_width": 320,
                "src": "https://instagram.fsaw1-6.fna.fbcdn.net/t51.2885-15/s320x320/e35/c0.56.850.850/19534841_120481221902052_5708394887984971776_n.jpg"
            },
            {
                "config_height": 480,
                "config_width": 480,
                "src": "https://instagram.fsaw1-6.fna.fbcdn.net/t51.2885-15/s480x480/e35/c0.56.850.850/19534841_120481221902052_5708394887984971776_n.jpg"
            },
            {
                "config_height": 640,
                "config_width": 640,
                "src": "https://instagram.fsaw1-6.fna.fbcdn.net/t51.2885-15/s640x640/sh0.08/e35/c0.56.850.850/19534841_120481221902052_5708394887984971776_n.jpg"
            }
        ],
        "thumbnail_src": "https://instagram.fsaw1-6.fna.fbcdn.net/t51.2885-15/s640x640/sh0.08/e35/c0.56.850.850/19534841_120481221902052_5708394887984971776_n.jpg",
        "urls": [
            "https://instagram.fsaw1-6.fna.fbcdn.net/t51.2885-15/e35/19534841_120481221902052_5708394887984971776_n.jpg"
        ]
    },
    {
        "__typename": "GraphSidecar",
        "comments_disabled": false,
        "dimensions": {
            "height": 1080,
            "width": 1080
        },
        "display_url": "https://instagram.fsaw1-6.fna.fbcdn.net/t51.2885-15/e35/19227331_246425552508356_4174564373257256960_n.jpg",
        "edge_media_preview_like": {
            "count": 111
        },
        "edge_media_to_caption": {
            "edges": [
                {
                    "node": {
                        "text": "Miller drinking, chicken eating, dress so fly\nI got friends in high places that are keeping me high! \nAlready missed you 😔#germany #BEST"
                    }
                }
            ]
        },
        "edge_media_to_comment": {
            "count": 1
        },
        "id": "1537159404208713586",
        "is_video": false,
        "owner": {
            "id": "1942768511"
        },
        "shortcode": "BVVFlV7Au9y",
        "tags": [
            "BEST",
            "germany"
        ],
        "taken_at_timestamp": 1497463702,
        "thumbnail_resources": [
            {
                "config_height": 150,
                "config_width": 150,
                "src": "https://instagram.fsaw1-6.fna.fbcdn.net/t51.2885-15/s150x150/e35/19227331_246425552508356_4174564373257256960_n.jpg"
            },
            {
                "config_height": 240,
                "config_width": 240,
                "src": "https://instagram.fsaw1-6.fna.fbcdn.net/t51.2885-15/s240x240/e35/19227331_246425552508356_4174564373257256960_n.jpg"
            },
            {
                "config_height": 320,
                "config_width": 320,
                "src": "https://instagram.fsaw1-6.fna.fbcdn.net/t51.2885-15/s320x320/e35/19227331_246425552508356_4174564373257256960_n.jpg"
            },
            {
                "config_height": 480,
                "config_width": 480,
                "src": "https://instagram.fsaw1-6.fna.fbcdn.net/t51.2885-15/s480x480/e35/19227331_246425552508356_4174564373257256960_n.jpg"
            },
            {
                "config_height": 640,
                "config_width": 640,
                "src": "https://instagram.fsaw1-6.fna.fbcdn.net/t51.2885-15/s640x640/sh0.08/e35/19227331_246425552508356_4174564373257256960_n.jpg"
            }
        ],
        "thumbnail_src": "https://instagram.fsaw1-6.fna.fbcdn.net/t51.2885-15/s640x640/sh0.08/e35/19227331_246425552508356_4174564373257256960_n.jpg",
        "urls": [
            "https://instagram.fsaw1-6.fna.fbcdn.net/t51.2885-15/e35/19227331_246425552508356_4174564373257256960_n.jpg",
            "https://instagram.fsaw1-6.fna.fbcdn.net/t51.2885-15/e35/19052233_1828047924190084_6638080506694991872_n.jpg",
            "https://instagram.fsaw1-6.fna.fbcdn.net/t51.2885-15/e35/19120293_1200009753459733_5273548067948199936_n.jpg",
            "https://instagram.fsaw1-6.fna.fbcdn.net/t51.2885-15/e35/19227267_329460764154687_1101738340685709312_n.jpg",
            "https://instagram.fsaw1-6.fna.fbcdn.net/t51.2885-15/e35/19051800_113697805901096_2976591311710191616_n.jpg",
            "https://instagram.fsaw1-6.fna.fbcdn.net/t51.2885-15/e35/19122417_1941157432834236_5829998258381914112_n.jpg",
            "https://instagram.fsaw1-6.fna.fbcdn.net/t51.2885-15/e35/19120337_172148003321886_8859701058365030400_n.jpg",
            "https://instagram.fsaw1-6.fna.fbcdn.net/t51.2885-15/e35/19120507_450165192006989_3575045376060686336_n.jpg",
            "https://instagram.fsaw1-6.fna.fbcdn.net/t51.2885-15/e35/19120940_1745811545717707_1411952171934547968_n.jpg"
        ]
    },
    {
        "__typename": "GraphImage",
        "comments_disabled": false,
        "dimensions": {
            "height": 1350,
            "width": 1080
        },
        "display_url": "https://instagram.fsaw1-6.fna.fbcdn.net/t51.2885-15/e35/18889017_462853580716698_4320048272921067520_n.jpg",
        "edge_media_preview_like": {
            "count": 158
        },
        "edge_media_to_caption": {
            "edges": [
                {
                    "node": {
                        "text": "'Dear old world', she murmured, 'you are very lovely, and I am glad to be alive in you.'"
                    }
                }
            ]
        },
        "edge_media_to_comment": {
            "count": 0
        },
        "id": "1533481329448990542",
        "is_video": false,
        "owner": {
            "id": "1942768511"
        },
        "shortcode": "BVIBST3gDdO",
        "tags": [],
        "taken_at_timestamp": 1497025241,
        "thumbnail_resources": [
            {
                "config_height": 150,
                "config_width": 150,
                "src": "https://instagram.fsaw1-6.fna.fbcdn.net/t51.2885-15/s150x150/e35/c0.135.1080.1080/18889017_462853580716698_4320048272921067520_n.jpg"
            },
            {
                "config_height": 240,
                "config_width": 240,
                "src": "https://instagram.fsaw1-6.fna.fbcdn.net/t51.2885-15/s240x240/e35/c0.135.1080.1080/18889017_462853580716698_4320048272921067520_n.jpg"
            },
            {
                "config_height": 320,
                "config_width": 320,
                "src": "https://instagram.fsaw1-6.fna.fbcdn.net/t51.2885-15/s320x320/e35/c0.135.1080.1080/18889017_462853580716698_4320048272921067520_n.jpg"
            },
            {
                "config_height": 480,
                "config_width": 480,
                "src": "https://instagram.fsaw1-6.fna.fbcdn.net/t51.2885-15/s480x480/e35/c0.135.1080.1080/18889017_462853580716698_4320048272921067520_n.jpg"
            },
            {
                "config_height": 640,
                "config_width": 640,
                "src": "https://instagram.fsaw1-6.fna.fbcdn.net/t51.2885-15/s640x640/sh0.08/e35/c0.135.1080.1080/18889017_462853580716698_4320048272921067520_n.jpg"
            }
        ],
        "thumbnail_src": "https://instagram.fsaw1-6.fna.fbcdn.net/t51.2885-15/s640x640/sh0.08/e35/c0.135.1080.1080/18889017_462853580716698_4320048272921067520_n.jpg",
        "urls": [
            "https://instagram.fsaw1-6.fna.fbcdn.net/t51.2885-15/e35/18889017_462853580716698_4320048272921067520_n.jpg"
        ]
    },
    {
        "__typename": "GraphImage",
        "comments_disabled": false,
        "dimensions": {
            "height": 809,
            "width": 1080
        },
        "display_url": "https://instagram.fsaw1-6.fna.fbcdn.net/t51.2885-15/e35/18948262_1457552654546230_8860834745047580672_n.jpg",
        "edge_media_preview_like": {
            "count": 149
        },
        "edge_media_to_caption": {
            "edges": [
                {
                    "node": {
                        "text": "You wake up in the morning and you're head feels twice the size"
                    }
                }
            ]
        },
        "edge_media_to_comment": {
            "count": 0
        },
        "id": "1531855582775076351",
        "is_video": false,
        "owner": {
            "id": "1942768511"
        },
        "shortcode": "BVCPolSgeX_",
        "tags": [],
        "taken_at_timestamp": 1496831437,
        "thumbnail_resources": [
            {
                "config_height": 150,
                "config_width": 150,
                "src": "https://instagram.fsaw1-6.fna.fbcdn.net/t51.2885-15/s150x150/e35/c135.0.809.809/18948262_1457552654546230_8860834745047580672_n.jpg"
            },
            {
                "config_height": 240,
                "config_width": 240,
                "src": "https://instagram.fsaw1-6.fna.fbcdn.net/t51.2885-15/s240x240/e35/c135.0.809.809/18948262_1457552654546230_8860834745047580672_n.jpg"
            },
            {
                "config_height": 320,
                "config_width": 320,
                "src": "https://instagram.fsaw1-6.fna.fbcdn.net/t51.2885-15/s320x320/e35/c135.0.809.809/18948262_1457552654546230_8860834745047580672_n.jpg"
            },
            {
                "config_height": 480,
                "config_width": 480,
                "src": "https://instagram.fsaw1-6.fna.fbcdn.net/t51.2885-15/s480x480/e35/c135.0.809.809/18948262_1457552654546230_8860834745047580672_n.jpg"
            },
            {
                "config_height": 640,
                "config_width": 640,
                "src": "https://instagram.fsaw1-6.fna.fbcdn.net/t51.2885-15/s640x640/sh0.08/e35/c135.0.809.809/18948262_1457552654546230_8860834745047580672_n.jpg"
            }
        ],
        "thumbnail_src": "https://instagram.fsaw1-6.fna.fbcdn.net/t51.2885-15/s640x640/sh0.08/e35/c135.0.809.809/18948262_1457552654546230_8860834745047580672_n.jpg",
        "urls": [
            "https://instagram.fsaw1-6.fna.fbcdn.net/t51.2885-15/e35/18948262_1457552654546230_8860834745047580672_n.jpg"
        ]
    },
    {
        "__typename": "GraphImage",
        "comments_disabled": false,
        "dimensions": {
            "height": 954,
            "width": 1080
        },
        "display_url": "https://instagram.fsaw1-6.fna.fbcdn.net/t51.2885-15/e35/18160298_211362632695324_3643587784179974144_n.jpg",
        "edge_media_preview_like": {
            "count": 155
        },
        "edge_media_to_caption": {
            "edges": [
                {
                    "node": {
                        "text": "Efekt yapmıycam çünkü istanbul her haliyle güzel"
                    }
                }
            ]
        },
        "edge_media_to_comment": {
            "count": 0
        },
        "id": "1503052887985644658",
        "is_video": false,
        "owner": {
            "id": "1942768511"
        },
        "shortcode": "BTb6qNbAmRy",
        "tags": [],
        "taken_at_timestamp": 1493397888,
        "thumbnail_resources": [
            {
                "config_height": 150,
                "config_width": 150,
                "src": "https://instagram.fsaw1-6.fna.fbcdn.net/t51.2885-15/s150x150/e35/c63.0.954.954/18160298_211362632695324_3643587784179974144_n.jpg"
            },
            {
                "config_height": 240,
                "config_width": 240,
                "src": "https://instagram.fsaw1-6.fna.fbcdn.net/t51.2885-15/s240x240/e35/c63.0.954.954/18160298_211362632695324_3643587784179974144_n.jpg"
            },
            {
                "config_height": 320,
                "config_width": 320,
                "src": "https://instagram.fsaw1-6.fna.fbcdn.net/t51.2885-15/s320x320/e35/c63.0.954.954/18160298_211362632695324_3643587784179974144_n.jpg"
            },
            {
                "config_height": 480,
                "config_width": 480,
                "src": "https://instagram.fsaw1-6.fna.fbcdn.net/t51.2885-15/s480x480/e35/c63.0.954.954/18160298_211362632695324_3643587784179974144_n.jpg"
            },
            {
                "config_height": 640,
                "config_width": 640,
                "src": "https://instagram.fsaw1-6.fna.fbcdn.net/t51.2885-15/s640x640/sh0.08/e35/c63.0.954.954/18160298_211362632695324_3643587784179974144_n.jpg"
            }
        ],
        "thumbnail_src": "https://instagram.fsaw1-6.fna.fbcdn.net/t51.2885-15/s640x640/sh0.08/e35/c63.0.954.954/18160298_211362632695324_3643587784179974144_n.jpg",
        "urls": [
            "https://instagram.fsaw1-6.fna.fbcdn.net/t51.2885-15/e35/18160298_211362632695324_3643587784179974144_n.jpg"
        ]
    }
]